{"cameraMode":{"drawMode":0,"name":"Shaded","section":"Shading Mode"},"sceneLighting":false,"audioPlay":false,"sceneViewState":{"m_AlwaysRefresh":false,"showFog":true,"showSkybox":false,"showFlares":true,"showImageEffects":true,"showParticleSystems":true,"showVisualEffectGraphs":true,"m_FxEnabled":true},"in2DMode":false,"pivot":{"x":-0.017719745635986329,"y":-0.053752776235342029,"z":0.23939049243927003},"rotation":{"x":0.19221827387809754,"y":0.5595937967300415,"z":-0.13534744083881379,"w":0.7947259545326233},"size":3.4970972537994386,"orthographic":false}